COPYING.md
LICENSE.md
README.md
pyproject.toml
setup.py
LAMINAR/__init__.py
LAMINAR/Flow/OTFlow.py
LAMINAR/Flow/__init__.py
LAMINAR/LAMINAR/LAMINAR.py
LAMINAR/LAMINAR/__init__.py
LAMINAR/utils/__init__.py
LAMINAR/utils/dijkstra.py
LAMINAR/utils/gaussian2uniform.py
LAMINAR/utils/geodesics.py
LAMINAR/utils/standardize.py
LAMINAR/utils/tensor_visualisation.py
laminar_learn.egg-info/PKG-INFO
laminar_learn.egg-info/SOURCES.txt
laminar_learn.egg-info/dependency_links.txt
laminar_learn.egg-info/requires.txt
laminar_learn.egg-info/top_level.txt
tests/test_LAMINAR.py